setup.py
highfre/__init__.py
highfre/bitmex_etc.py
highfre/bitmex_ws.py
highfre/crawl_data.py
highfre/filter_data.py
highfre/main.py
highfre/model.py
highfre/okex_ws.py
highfre/trade_conf.py
highfre/trader.py
highfre/wave_trader.py
highfre.egg-info/PKG-INFO
highfre.egg-info/SOURCES.txt
highfre.egg-info/dependency_links.txt
highfre.egg-info/requires.txt
highfre.egg-info/top_level.txt