Metadata-Version: 1.0
Name: highfre
Version: 1.0.0
Summary: An highfre demo
Home-page: https://github.com/confiself/highfre
Author: confiself
Author-email: 1120396510@qq.com
License: MIT Licence
Keywords: pip,highfre
Platform: any
